pyrathon_news/__init__.py
pyrathon_news/client.py
pyrathon_news-0.1.0.dist-info/METADATA
pyrathon_news-0.1.0.dist-info/WHEEL
pyrathon_news-0.1.0.dist-info/top_level.txt
pyrathon_news-0.1.0.dist-info/RECORD
