Metadata-Version: 2.4
Name: pyrathon-news
Version: 0.1.0
Summary: Cliente oficial para consumir la API de Pyrathon News
Home-page: https://githu0b.com/Pyramoidix
Author: pyramoidix
Author-email: Tu Nombre <tuemail@example.com>
License: MIT
Project-URL: Homepage, https://github.com/tuusuario/pyrathon-news
Requires-Python: >=3.7
Requires-Dist: requests>=2.0.0
Dynamic: author
Dynamic: home-page
Dynamic: requires-python
